scrud_django/__init__.py
scrud_django/apps.py
scrud_django/asgi.py
scrud_django/conf.py
scrud_django/decorators.py
scrud_django/exceptions.py
scrud_django/headers.py
scrud_django/migrations/0001_initial.py
scrud_django/migrations/0002_auto_20200826_0345.py
scrud_django/migrations/0003_resourcetype_revision.py
scrud_django/migrations/0004_auto_20210306_1600.py
scrud_django/migrations/0005_fix_resource_content_column_type.py
scrud_django/migrations/0006_resourcetype_uses_reversion.py
scrud_django/migrations/__init__.py
scrud_django/mixins/__init__.py
scrud_django/mixins/resource_mixin.py
scrud_django/mixins/serializer_mixins.py
scrud_django/mixins/view_mixins.py
scrud_django/models/__init__.py
scrud_django/models/resource.py
scrud_django/models/resource_type.py
scrud_django/paginations.py
scrud_django/permissions.py
scrud_django/registration.py
scrud_django/scrud_signals.py
scrud_django/search_indexes.py
scrud_django/serializers.py
scrud_django/settings.py
scrud_django/static/IndexingPolicy-ld.json
scrud_django/static/IndexingPolicy-schema.json
scrud_django/static/WorkflowPolicy-ld.json
scrud_django/static/WorkflowPolicy-schema.json
scrud_django/static/__init__.py
scrud_django/urls.py
scrud_django/utils.py
scrud_django/validators.py
scrud_django/views.py
scrud_django/workflow.py
scrud_django/wsgi.py
scrud_django-0.11.0.dist-info/LICENSE
scrud_django-0.11.0.dist-info/WHEEL
scrud_django-0.11.0.dist-info/METADATA
scrud_django-0.11.0.dist-info/RECORD
